[
  {
    "word": "Write off",
    "meaning": "To accept that money is lost or that an asset is no longer valuable",
    "shortMeaning": "accept a loss",
    "example": "The company had to write off the old computers as they were broken and useless.",
    "example2": "The bank decided to write off the unpaid debt.",
    "example3": "It's better to write off the project now than to keep wasting money on it.",
    "Explanation": "In business and accounting, 'write off' means removing something from the records because it has no value. For example, if a laptop is destroyed, the company 'writes it off' their taxes because it's no longer an asset they own. In a more general sense, it means to give up on something that isn't working. It is a way of cleaning up a balance sheet or a plan by admitting that a certain investment or piece of equipment is now worthless. It helps in keeping financial records honest and up to date.",
    "synonyms": [
      "cancel",
      "discard",
      "write down"
    ],
    "antonyms": [
      "invest",
      "capitalize",
      "save"
    ],
    "nounForm": "write-off",
    "verbForm": "write off",
    "adjectiveForm": "N/A",
    "partOfSpeech": "phrasal verb / noun",
    "commonContext": "Accounting, business, and general decision making",
    "usageTip": "Use 'write off' when you are officially acknowledging a loss.",
    "commonMistake": "Confusing 'write off' with 'writing off' (the act of scribbling); in business, it's a financial term.",
    "collocations": [
      "tax write off",
      "total write off",
      "write off a debt"
    ]
  },
  {
    "word": "Write off",
    "meaning": "To officially cancel a debt, asset, or value from a financial ledger because it is deemed uncollectible or useless",
    "shortMeaning": "cancel debt or asset",
    "example": "The company had to write off the old computers as a loss.",
    "example2": "The bank decided to write off the outstanding loan after the client went bankrupt.",
    "example3": "You can write off certain business expenses to reduce your taxable income.",
    "Explanation": "The phrase 'write off' is an accounting and financial term used when an asset or a bad debt is recognized as having no remaining value. When an organization writes off an item, it removes it from the balance sheet and records it as an expense or a loss. In a broader, casual context, 'write off' can also mean to dismiss someone or something as a failure or a lost cause. However, in professional and corporate contexts, it remains strictly tied to financial records and asset devaluation.",
    "synonyms": [
      "cancel",
      "cancel debt",
      "charge off"
    ],
    "antonyms": [
      "capitalize",
      "collect",
      "recover"
    ],
    "nounForm": "write-off",
    "verbForm": "write off",
    "adjectiveForm": "written-off",
    "partOfSpeech": "verb phrase",
    "commonContext": "Accounting, finance, business management, tax reporting",
    "usageTip": "Keep the phrase as two separate words for the verb ('write off') and use a hyphen for the noun form ('write-off').",
    "commonMistake": "Spelling the verb form with a hyphen like 'write-off the debt' instead of 'write off the debt'.",
    "collocations": [
      "write off bad debts",
      "write off an asset",
      "tax write off"
    ]
  }
]