[
  {
    "word": "Silent",
    "meaning": "Running without providing output or user interaction.",
    "shortMeaning": "no output",
    "example": "The installer runs in silent mode by default.",
    "example2": "We implemented a silent update to avoid interrupting users.",
    "example3": "The error was silent, making debugging difficult.",
    "Explanation": "A 'silent' operation runs in the background without prompting the user or providing visible feedback. 'Silent installs' or 'silent updates' are useful for automating deployment across thousands of machines. However, a 'silent error' is dangerous because it fails without providing any logs or notice, which can make diagnosing issues incredibly frustrating. It is an effective tool for automation, but must be designed to log errors effectively for developers.",
    "synonyms": [
      "unnoticed",
      "background",
      "non-interactive"
    ],
    "antonyms": [
      "verbose",
      "interactive",
      "audible"
    ],
    "nounForm": "silence",
    "verbForm": "N/A",
    "adjectiveForm": "silent",
    "partOfSpeech": "adjective",
    "commonContext": "Automation, deployment, debugging",
    "usageTip": "Use 'silent' to describe background, non-interactive processes.",
    "commonMistake": "Allowing silent errors to pass without logging.",
    "collocations": [
      "silent mode",
      "silent install",
      "silent error"
    ]
  },
  {
    "word": "Silent",
    "meaning": "Functioning without making noise or showing alerts",
    "shortMeaning": "no sound or output",
    "example": "The installation runs in silent mode without user prompts.",
    "example2": "The error was silent, failing without an alert.",
    "example3": "Keep the server rack silent during maintenance.",
    "Explanation": "In IT, 'silent' often refers to processes that run in the background without user interaction, or failures that occur without showing an error message. A 'silent install' is a common example where no setup window appears. It can also describe hardware that produces no noise. The noun form is 'silence'. It is vital to design systems that are not 'silently failing', as that makes debugging very difficult.",
    "synonyms": [
      "quiet",
      "noiseless",
      "unnoticed"
    ],
    "antonyms": [
      "noisy",
      "audible",
      "loud"
    ],
    "nounForm": "silence",
    "verbForm": "N/A",
    "adjectiveForm": "silent",
    "partOfSpeech": "adjective",
    "commonContext": "Software installation, hardware, error logs",
    "usageTip": "Use 'silent' to describe automated processes or hidden failures.",
    "commonMistake": "Confusing a 'silent failure' with a successful operation.",
    "collocations": [
      "silent installation",
      "silent mode",
      "silent failure"
    ]
  }
]